LICENSE.txt
README.md
setup.py
codecon/__init__.py
codecon/cl_nlp.py
codecon/cl_nlp_findtrain.py
codecon/cl_nlp_pred.py
codecon/cl_nlp_train.py
codecon/gai_nlp.py
codecon/tp_nlp.py
codecon.egg-info/PKG-INFO
codecon.egg-info/SOURCES.txt
codecon.egg-info/dependency_links.txt
codecon.egg-info/requires.txt
codecon.egg-info/top_level.txt
codecon/data/__init__.py
codecon/data/cn_stopwords.txt
codecon/utils/CustomDataset.py
codecon/utils/FileReader.py
codecon/utils/FocalLoss.py
codecon/utils/__init__.py