Metadata-Version: 2.1
Name: codecon
Version: 0.9.3
Summary: A machine learning library for economists
Home-page: https://github.com/mickwzh/codecon
Author: Zhaohui Wang
Author-email: mickwang@connect.hku.hk
Requires-Python: >=3.6
License-File: LICENSE.txt
Requires-Dist: pip
Requires-Dist: pandas
Requires-Dist: numpy<2
Requires-Dist: scikit-learn
Requires-Dist: transformers
Requires-Dist: torch
Requires-Dist: xlrd
Requires-Dist: tqdm
Requires-Dist: jieba
Requires-Dist: importlib.resources
Requires-Dist: psutil
Requires-Dist: matplotlib
Requires-Dist: seaborn
Requires-Dist: gensim
Requires-Dist: bertopic
Requires-Dist: nltk
Requires-Dist: openai
Requires-Dist: openpyxl
